{"type": "Feature", "id": 56558440, "geometry": {"type": "Point", "coordinates": [32.917999, -1.959]}, "properties": {"woe:id": 56558440, "woe:parent_id": 56025210, "woe:name": "Muriti", "woe:placetype": 7, "woe:placetype_name": "Town", "woe:lang": "ENG", "iso:country": "TZ", "meta:provider": ["geoplanet:7.10.0", "geoplanet:8.0.0", "woeplanet:8.0.0"], "meta:indexed": "2020-08-21T14:29:58.896063", "woe:hierarchy": {"continent": 23424973, "country": 23424973, "town": 0, "planet": 1, "county": 56025210, "suburb": 0, "state": 2347363, "region": 0, "localadmin": 0}, "meta:updated": "2020-10-14T11:05:42.638752", "woe:timezone_id": 28350697, "woe:hash": "kxxkv565uzzj", "geom:min_latitude": -1.959, "woe:centroid": [32.917999, -1.959], "geom:latitude": -1.959, "woe:max_longitude": 32.917999, "geom:max_longitude": 32.917999, "geom:centroid": [32.917999, -1.959], "geom:max_latitude": -1.959, "woe:min_latitude": -1.959, "woe:min_longitude": 32.917999, "geom:longitude": 32.917999, "geom:hash": "kxxkv565uzzj", "woe:latitude": -1.959, "geom:min_longitude": 32.917999, "woe:longitude": 32.917999, "woe:max_latitude": -1.959, "woe:repo": "woeplanet-town-tz", "geom:area": 0.0, "woe:scale": 16}}